{
  "version": "1.0",
  "generated_at": "2025-11-14T23:27:53Z",
  "generator": "zyra.wizard.manifest",
  "domains": {
    "acquire": "acquire.json",
    "decide": "decide.json",
    "decimate": "decimate.json",
    "disseminate": "disseminate.json",
    "export": "export.json",
    "import": "import.json",
    "narrate": "narrate.json",
    "optimize": "optimize.json",
    "process": "process.json",
    "render": "render.json",
    "run": "run.json",
    "search": "search.json",
    "simulate": "simulate.json",
    "transform": "transform.json",
    "verify": "verify.json",
    "visualize": "visualize.json"
  }
}
